LICENSE.txt
MANIFEST.in
README.md
setup.py
cave/__init__.py
cave/range.py
cave/src/__init__.py
cave/src/os_types.py
cave/src/autoinstall/__init__.py
cave/src/autoinstall/cdrom.py
cave/src/autoinstall/linux/__init__.py
cave/src/autoinstall/linux/cloud-init-meta.jinja.yaml
cave/src/autoinstall/linux/cloud-init-network.jinja.yml
cave/src/autoinstall/linux/cloud-init-user.jinja.yaml
cave/src/autoinstall/linux/cloudinit.py
cave/src/autoinstall/windows/__init__.py
cave/src/autoinstall/windows/first_logon_script.ps1
cave/src/autoinstall/windows/logon_script_generator.py
cave/src/autoinstall/windows/windows_client/__init__.py
cave/src/autoinstall/windows/windows_client/autounattend.jinja.xml
cave/src/autoinstall/windows/windows_client/autounattend.py
cave/src/autoinstall/windows/windows_gpt_tpm/__init__.py
cave/src/autoinstall/windows/windows_gpt_tpm/autounattend.py
cave/src/autoinstall/windows/windows_gpt_tpm/autounattend_gpt.jinja.xml
cave/src/autoinstall/windows/windows_server/__init__.py
cave/src/autoinstall/windows/windows_server/autounattend.py
cave/src/autoinstall/windows/windows_server/autounattend_windows_server.jinja.xml
cave/src/domains/__init__.py
cave/src/domains/filter.xml
cave/src/domains/interface.py
cave/src/domains/templated_libvirt_domain.py
cave/src/domains/domain_linux/__init__.py
cave/src/domains/domain_linux/domain_linux.jinja.xml
cave/src/domains/domain_linux/domain_linux.py
cave/src/domains/domain_windows/__init__.py
cave/src/domains/domain_windows/domain_windows.jinja.xml
cave/src/domains/domain_windows/domain_windows.py
cave/src/domains/domain_windows_tpm/__init__.py
cave/src/domains/domain_windows_tpm/domain_windows_tpm.jinja.xml
cave/src/domains/domain_windows_tpm/domain_windows_tpm.py
cave/src/networks/__init__.py
cave/src/networks/network/__init__.py
cave/src/networks/network/filter.jinja.xml
cave/src/networks/network/network.jinja.xml
cave/src/networks/network/network.py
cave/src/pools/__init__.py
cave/src/pools/dir_pool/__init__.py
cave_infra.egg-info/PKG-INFO
cave_infra.egg-info/SOURCES.txt
cave_infra.egg-info/dependency_links.txt
cave_infra.egg-info/requires.txt
cave_infra.egg-info/top_level.txt
