Metadata-Version: 2.1
Name: cave-infra
Version: 0.1.4
Summary: Automation toolkit for automated provisioning virtual infrastructure.
Home-page: https://github.com/sn0ja/cave/
Author: sn0ja
License-File: LICENSE.txt
Requires-Dist: Jinja2==3.1.6
Requires-Dist: libvirt-python==11.4.0
Requires-Dist: MarkupSafe==3.0.2
